aieng_bot/__init__.py
aieng_bot/cli.py
aieng_bot/config.py
aieng_bot/py.typed
aieng_bot/_cli/__init__.py
aieng_bot/_cli/help_config.py
aieng_bot/_cli/main.py
aieng_bot/_cli/utils.py
aieng_bot/_cli/commands/__init__.py
aieng_bot/_cli/commands/classify.py
aieng_bot/_cli/commands/fix.py
aieng_bot/agent_fixer/__init__.py
aieng_bot/agent_fixer/fixer.py
aieng_bot/agent_fixer/models.py
aieng_bot/agent_fixer/prompts.py
aieng_bot/classifier/__init__.py
aieng_bot/classifier/classifier.py
aieng_bot/classifier/models.py
aieng_bot/classifier/prompts.py
aieng_bot/observability/__init__.py
aieng_bot/observability/activity_logger.py
aieng_bot/observability/classifiers.py
aieng_bot/observability/extractors.py
aieng_bot/observability/parsers.py
aieng_bot/observability/processors.py
aieng_bot/observability/storage.py
aieng_bot/observability/tracer.py
aieng_bot/utils/__init__.py
aieng_bot/utils/github_client.py
aieng_bot/utils/logging.py
aieng_bot-0.7.0.dist-info/METADATA
aieng_bot-0.7.0.dist-info/WHEEL
aieng_bot-0.7.0.dist-info/entry_points.txt
aieng_bot-0.7.0.dist-info/licenses/LICENSE.md
aieng_bot-0.7.0.dist-info/RECORD
